fixdatalink/__init__.py
fixdatalink/analytics.py
fixdatalink/batch_stream.py
fixdatalink/collect_plugins.py
fixdatalink/py.typed
fixdatalink/remote_graph.py
fixdatalink/schema_utils.py
fixdatalink/show_progress.py
fixdatalink/snowflake.py
fixdatalink/sql.py
fixdatalink/arrow/__init__.py
fixdatalink/arrow/config.py
fixdatalink/arrow/model.py
fixdatalink/arrow/type_converter.py
fixdatalink/arrow/writer.py
fixdatalink-2.0.2.dist-info/LICENSE
fixdatalink-2.0.2.dist-info/METADATA
fixdatalink-2.0.2.dist-info/WHEEL
fixdatalink-2.0.2.dist-info/top_level.txt
fixdatalink-2.0.2.dist-info/RECORD
