Metadata-Version: 2.1
Name: fixdatalink
Version: 2.0.2
Summary: Data Pipelines for Fix infrastructure data.
Author: Some Engineering Inc.
License: GNU AFFERO GENERAL PUBLIC LICENSE
Project-URL: Documentation, https://fix.com
Project-URL: Source, https://github.com/someengineering/fixdatalink
Keywords: data source,data sink,data synchronization,data pipeline
Classifier: Development Status :: 4 - Beta
Classifier: Intended Audience :: System Administrators
Classifier: Intended Audience :: Information Technology
Classifier: License :: OSI Approved :: GNU Affero General Public License v3 or later (AGPLv3+)
Classifier: Programming Language :: Python :: 3.11
Classifier: Operating System :: POSIX :: Linux
Classifier: Operating System :: Unix
Classifier: Environment :: Console
Classifier: Natural Language :: English
Classifier: Topic :: Security
Classifier: Topic :: Utilities
Requires-Python: >=3.11
License-File: LICENSE
Requires-Dist: networkx
Requires-Dist: fixinventoryclient >=2.0.0
Requires-Dist: fixinventorylib
Requires-Dist: rich
Requires-Dist: sqlalchemy <2
Provides-Extra: dev
Requires-Dist: pip-tools ; extra == 'dev'
Requires-Dist: types-python-dateutil ; extra == 'dev'
Requires-Dist: types-requests ; extra == 'dev'
Requires-Dist: types-setuptools ; extra == 'dev'
Requires-Dist: types-six ; extra == 'dev'
Provides-Extra: extra
Requires-Dist: boto3 ; extra == 'extra'
Requires-Dist: urllib3 <2 ; extra == 'extra'
Requires-Dist: google-cloud-storage ; extra == 'extra'
Requires-Dist: pymysql ; extra == 'extra'
Requires-Dist: psycopg2-binary ; extra == 'extra'
Requires-Dist: pyarrow ; extra == 'extra'
Requires-Dist: snowflake-sqlalchemy ; extra == 'extra'
Provides-Extra: mysql
Requires-Dist: pymysql ; extra == 'mysql'
Provides-Extra: parquet
Requires-Dist: pyarrow ; extra == 'parquet'
Requires-Dist: boto3 ; extra == 'parquet'
Requires-Dist: google-cloud-storage ; extra == 'parquet'
Provides-Extra: postgres
Requires-Dist: psycopg2-binary ; extra == 'postgres'
Provides-Extra: snowflake
Requires-Dist: snowflake-sqlalchemy ; extra == 'snowflake'
Provides-Extra: test
Requires-Dist: black ; extra == 'test'
Requires-Dist: coverage ; extra == 'test'
Requires-Dist: flake8 ; extra == 'test'
Requires-Dist: hypothesis ; extra == 'test'
Requires-Dist: mypy ; extra == 'test'
Requires-Dist: pep8-naming ; extra == 'test'
Requires-Dist: posthog ; extra == 'test'
Requires-Dist: pylint ; extra == 'test'
Requires-Dist: pytest ; extra == 'test'
Requires-Dist: pytest-asyncio ; extra == 'test'
Requires-Dist: pytest-cov ; extra == 'test'
Requires-Dist: pytest-runner ; extra == 'test'
Requires-Dist: tox ; extra == 'test'
Requires-Dist: wheel ; extra == 'test'
Requires-Dist: fixinventory-plugin-example-collector ; extra == 'test'
